[
  {
    "teams": [
      "Bowling Green",
      "Indiana"
    ],
    "id": "80pmhk"
  },
  {
    "teams": [
      "Northwestern",
      "FAU"
    ],
    "id": "7rszcx"
  },
  {
    "teams": [
      "Michigan",
      "Notre Dame"
    ],
    "id": "7rqxmr"
  },
  {
    "teams": [
      "Louisiana-Monroe",
      "Buffalo"
    ],
    "id": "7t03cy"
  },
  {
    "teams": [
      "USF",
      "Ohio"
    ],
    "id": "80jdwz"
  },
  {
    "teams": [
      "Massachusetts",
      "Hawaii"
    ],
    "id": "7uuu4h"
  },
  {
    "teams": [
      "SMU",
      "Middle Tennessee"
    ],
    "id": "7t04rc"
  },
  {
    "teams": [
      "Cincinnati",
      "Florida State"
    ],
    "id": "7y32go"
  },
  {
    "teams": [
      "Kentucky",
      "Colorado"
    ],
    "id": "7rl7pq"
  },
  {
    "teams": [
      "Western Kentucky",
      "Ball State"
    ],
    "id": "7wilzp"
  },
  {
    "teams": [
      "Liberty",
      "Tulsa"
    ],
    "id": "80golb"
  },
  {
    "teams": [
      "New Mexico State",
      "Wyoming"
    ],
    "id": "7z1o09"
  },
  {
    "teams": [
      "Central Michigan",
      "Rice"
    ],
    "id": "7s1wln"
  },
  {
    "teams": [
      "LSU",
      "Nebraska"
    ],
    "id": "7t020d"
  },
  {
    "teams": [
      "Baylor",
      "Utah"
    ],
    "id": "7rksh1"
  },
  {
    "teams": [
      "Kansas",
      "Maryland"
    ],
    "id": "7rlbbx"
  },
  {
    "teams": [
      "Washington",
      "FIU"
    ],
    "id": "7zb59f"
  },
  {
    "teams": [
      "NC State",
      "Wake Forest"
    ],
    "id": "7sai4o"
  },
  {
    "teams": [
      "San Diego State",
      "Louisiana Tech"
    ],
    "id": "7ss972"
  },
  {
    "teams": [
      "Florida",
      "South Carolina"
    ],
    "id": "7rr1tz"
  },
  {
    "teams": [
      "Arizona",
      "Stanford"
    ],
    "id": "7txhb8"
  },
  {
    "teams": [
      "Iowa",
      "Alabama"
    ],
    "id": "7rksqm"
  },
  {
    "teams": [
      "North Carolina",
      "Houston"
    ],
    "id": "7y32l1"
  },
  {
    "teams": [
      "Utah State",
      "UAB"
    ],
    "id": "7tpdo9"
  },
  {
    "teams": [
      "Army",
      "UTSA"
    ],
    "id": "7yrrut"
  },
  {
    "teams": [
      "Connecticut",
      "Georgia Tech"
    ],
    "id": "7tovn0"
  },
  {
    "teams": [
      "Oklahoma",
      "Michigan State"
    ],
    "id": "7rl2xw"
  },
  {
    "teams": [
      "Oregon State",
      "Virginia Tech"
    ],
    "id": "7v4ko3"
  },
  {
    "teams": [
      "Colorado State",
      "USC"
    ],
    "id": "7thuo2"
  },
  {
    "teams": [
      "Oklahoma State",
      "Kansas State"
    ],
    "id": "7rlcuz"
  },
  {
    "teams": [
      "Southern Miss",
      "Georgia State"
    ],
    "id": "7z2mx8"
  },
  {
    "teams": [
      "Pittsburgh",
      "Old Dominion"
    ],
    "id": "7rlx11"
  },
  {
    "teams": [
      "Rutgers",
      "New Mexico"
    ],
    "id": "7u45bs"
  },
  {
    "teams": [
      "UNLV",
      "East Carolina"
    ],
    "id": "7ump3t"
  },
  {
    "teams": [
      "Washington State",
      "Air Force"
    ],
    "id": "7xvxuy"
  },
  {
    "teams": [
      "Eastern Michigan",
      "Kent State"
    ],
    "id": "8108wu"
  },
  {
    "teams": [
      "Georgia",
      "TCU"
    ],
    "id": "7rnxvy"
  },
  {
    "teams": [
      "Oregon",
      "Purdue"
    ],
    "id": "7rkvpr"
  },
  {
    "teams": [
      "UTEP",
      "Texas State"
    ],
    "id": "7xzvli"
  },
  {
    "teams": [
      "Missouri",
      "Tulane"
    ],
    "id": "7rmabp"
  },
  {
    "teams": [
      "Iowa State",
      "Illinois"
    ],
    "id": "7rl1ho"
  },
  {
    "teams": [
      "Marshall",
      "Georgia Southern"
    ],
    "id": "7sybif"
  },
  {
    "teams": [
      "Toledo",
      "West Virginia"
    ],
    "id": "7s9hyo"
  },
  {
    "teams": [
      "Louisville",
      "Clemson"
    ],
    "id": "7zlb4k"
  },
  {
    "teams": [
      "Wisconsin",
      "Texas"
    ],
    "id": "7rlngf"
  },
  {
    "teams": [
      "Northern Illinois",
      "San Jose State"
    ],
    "id": "7y3335"
  },
  {
    "teams": [
      "Virginia",
      "BYU"
    ],
    "id": "7rm9o0"
  },
  {
    "teams": [
      "Mississippi State",
      "Navy"
    ],
    "id": "7wqpy5"
  },
  {
    "teams": [
      "Boston College",
      "UCF"
    ],
    "id": "7ysqv1"
  },
  {
    "teams": [
      "Fresno State",
      "Western Michigan"
    ],
    "id": "7z3oi4"
  },
  {
    "teams": [
      "Arkansas",
      "South Alabama"
    ],
    "id": "7rlheu"
  },
  {
    "teams": [
      "Charlotte",
      "Louisiana-Lafayette"
    ],
    "id": "7v0poc"
  },
  {
    "teams": [
      "Duke",
      "Miami (FL)"
    ],
    "id": "87u897"
  },
  {
    "teams": [
      "Penn State",
      "Vanderbilt"
    ],
    "id": "7s2dnv"
  },
  {
    "teams": [
      "Coastal Carolina",
      "Texas Tech"
    ],
    "id": "7rnhg6"
  },
  {
    "teams": [
      "Arkansas State",
      "Ohio State"
    ],
    "id": "7v1esz"
  },
  {
    "teams": [
      "Appalachian State",
      "Nevada"
    ],
    "id": "7v2x72"
  },
  {
    "teams": [
      "Syracuse",
      "Tennessee"
    ],
    "id": "7ro819"
  },
  {
    "teams": [
      "Auburn",
      "Troy"
    ],
    "id": "7rmauc"
  },
  {
    "teams": [
      "Miami (OH)",
      "Minnesota"
    ],
    "id": "7rnjh1"
  },
  {
    "teams": [
      "Memphis",
      "Boise State"
    ],
    "id": "7tfc6f"
  },
  {
    "teams": [
      "Ole Miss",
      "Temple"
    ],
    "id": "7rrl7m"
  },
  {
    "teams": [
      "Texas A&M",
      "UCLA"
    ],
    "id": "7rkytq"
  },
  {
    "teams": [
      "North Texas",
      "Akron"
    ],
    "id": "7texgv"
  }
]